LICENSE.md
README.rst
setup.py
ipld/__init__.py
ipld/ipld.py
planetmint_ipld.egg-info/PKG-INFO
planetmint_ipld.egg-info/SOURCES.txt
planetmint_ipld.egg-info/dependency_links.txt
planetmint_ipld.egg-info/requires.txt
planetmint_ipld.egg-info/top_level.txt