Metadata-Version: 2.1
Name: planetmint-ipld
Version: 0.0.2
Summary: An IPLD implementation in Python
Author: Tim Daubenschuetz
Author-email: tim.daubenschuetz@gmail.com
License: MIT License
Keywords: ipld python ipfs bigchaindb
Classifier: Development Status :: 3 - Alpha
Classifier: Intended Audience :: Developers
Classifier: Natural Language :: English
Classifier: License :: OSI Approved :: MIT License
Classifier: Programming Language :: Python :: 3 :: Only
Classifier: Programming Language :: Python :: 3.4
Classifier: Programming Language :: Python :: 3.5
Classifier: Topic :: Software Development
Provides-Extra: test
Provides-Extra: dev
License-File: LICENSE.md
